README.md
setup.py
fib_py_example/__init__.py
fib_py_example.egg-info/PKG-INFO
fib_py_example.egg-info/SOURCES.txt
fib_py_example.egg-info/dependency_links.txt
fib_py_example.egg-info/entry_points.txt
fib_py_example.egg-info/top_level.txt
fib_py_example/cmd/__init__.py
fib_py_example/cmd/fib_numb.py
fib_py_example/fib_calcs/__init__.py
fib_py_example/fib_calcs/fib_number.py
fib_py_example/fib_calcs/fib_numbers.py
tests/fib_py/__init__.py
tests/fib_py/fib_calcs/__init__.py
tests/fib_py/fib_calcs/test_fib_number.py
tests/fib_py/fib_calcs/test_fib_numbers.py