Metadata-Version: 2.1
Name: fib-py-example
Version: 0.1.1
Summary: Calculates a Fibonacci number
Home-page: https://github.com/spartazhangzhang/python-fib
Author: David zhang
Author-email: spartazhangzhang@gmail.com
Classifier: Development Status :: 4 - Beta
Classifier: Programming Language :: Python :: 3
Classifier: Operating System :: OS Independent
Requires-Python: >=3.10
